{
    "ui": {
        "swipe_zone_bg_color": "#CCCCCC",
        "background": "#999999"
    },
    "world": {
        "food_outline": "#FF6666",
        "food": "#FF0000",
        "background": "#FFFFFF",
        "gridline": "#999999",
        "gridborder": "#999999"
    },
    "snakes": {
        "head_color_wheel": ["#0066CC", "#D19300", "#9400D3", "#008000"],
        "tail_color_wheel": ["#0088EE", "#F3B500", "#E94EE9", "#006400"],
        "tail_decay_first": "#8B0000",
        "tail_decay_final": "#FFD6D6",
        "head_decay_first": "#640000",
        "head_decay_final": "#FFD6D6",
        "inspect": "#CCCCCC"
    }
}
